{
  "frames": {
    "bomb-01": {
      "frame": {
        "x": 0,
        "y": 0,
        "w": 256,
        "h": 256
      }
    },
    "bomb-02": {
      "frame": {
        "x": 258,
        "y": 0,
        "w": 256,
        "h": 256
      }
    },
    "bomb-03": {
      "frame": {
        "x": 516,
        "y": 0,
        "w": 256,
        "h": 256
      }
    },
    "bomb-04": {
      "frame": {
        "x": 0,
        "y": 258,
        "w": 256,
        "h": 256
      }
    },
    "bomb-05": {
      "frame": {
        "x": 0,
        "y": 516,
        "w": 256,
        "h": 256
      }
    },
    "bomb-06": {
      "frame": {
        "x": 258,
        "y": 258,
        "w": 256,
        "h": 256
      }
    },
    "bomb-07": {
      "frame": {
        "x": 258,
        "y": 516,
        "w": 256,
        "h": 256
      }
    },
    "bomb-08": {
      "frame": {
        "x": 516,
        "y": 258,
        "w": 256,
        "h": 256
      }
    },
    "bomb-09": {
      "frame": {
        "x": 516,
        "y": 516,
        "w": 256,
        "h": 256
      }
    },
    "bomb-10": {
      "frame": {
        "x": 774,
        "y": 0,
        "w": 256,
        "h": 256
      }
    },
    "bomb-11": {
      "frame": {
        "x": 774,
        "y": 258,
        "w": 256,
        "h": 256
      }
    },
    "bomb-12": {
      "frame": {
        "x": 774,
        "y": 516,
        "w": 256,
        "h": 256
      }
    }
  },
  "meta": {
    "image": "bomb_fuse.png",
    "size": {
      "w": 2048,
      "h": 1024
    }
  }
}
